rsstail/__init__.py
rsstail/__main__.py
rsstail/formatter.py
rsstail/main.py
rsstail-0.6.0.dist-info/LICENSE.txt
rsstail-0.6.0.dist-info/METADATA
rsstail-0.6.0.dist-info/WHEEL
rsstail-0.6.0.dist-info/entry_points.txt
rsstail-0.6.0.dist-info/top_level.txt
rsstail-0.6.0.dist-info/RECORD
