Metadata-Version: 2.2
Name: rsstail
Version: 0.6.0
Summary: A command-line syndication feed monitor mimicking tail -f
Author-email: Georgi Valkov <georgi.t.valkov@gmail.com>
License: Copyright (c) 2011-2022 Georgi Valkov. All rights reserved.
Project-URL: Homepage, https://github.com/gvalkov/rsstail.py
Keywords: rss,tail,feed,feedparser
Classifier: Environment :: Console
Classifier: Topic :: Utilities
Classifier: Operating System :: OS Independent
Classifier: Programming Language :: Python :: 3
Classifier: License :: OSI Approved :: BSD License
Classifier: Development Status :: 5 - Production/Stable
Requires-Python: >=3.9
License-File: LICENSE.txt
Requires-Dist: feedparser>=6.0.11
Provides-Extra: test
Requires-Dist: tox>=4.24.1; extra == "test"
Requires-Dist: pytest>=8.3.5; extra == "test"
Requires-Dist: pytest-cov>=6.0.0; extra == "test"
